emp/__init__.py
emp/_version.py
emp/pymp_iterator.py
emp/pymp_mapper.py
emp/ray_backend.py
emp/ray_dataloader.py
emp/ray_iterator.py
emp/ray_mapper.py
emp/task.py
emp/utils.py
PyEMP-1.0.0.dist-info/LICENSE
PyEMP-1.0.0.dist-info/METADATA
PyEMP-1.0.0.dist-info/WHEEL
PyEMP-1.0.0.dist-info/top_level.txt
PyEMP-1.0.0.dist-info/RECORD
