Metadata-Version: 2.1
Name: PyEMP
Version: 1.0.0
Summary: UNKNOWN
Home-page: https://github.com/WarBean/emp
Author: UNKNOWN
Author-email: UNKNOWN
License: UNKNOWN
Platform: UNKNOWN
Requires-Dist: ray
